trigslink/__init__.py
trigslink/ascii_logo.py
trigslink/tunnel.py
trigslink_tunnel-0.1.2.dist-info/METADATA
trigslink_tunnel-0.1.2.dist-info/WHEEL
trigslink_tunnel-0.1.2.dist-info/entry_points.txt
trigslink_tunnel-0.1.2.dist-info/top_level.txt
trigslink_tunnel-0.1.2.dist-info/RECORD
