Metadata-Version: 2.4
Name: trigslink-tunnel
Version: 0.1.2
Summary: A CLI to create cloudflare tunnels for Trigslink MCP services
Author: Aakash
Keywords: trigslink cli tunnel cloudflare web3
Classifier: Programming Language :: Python :: 3
Classifier: License :: OSI Approved :: MIT License
Requires-Python: >=3.7
Dynamic: author
Dynamic: classifier
Dynamic: description
Dynamic: description-content-type
Dynamic: keywords
Dynamic: requires-python
Dynamic: summary
